[
    {
        "date": "2024-01-01",
        "localName": "Any nou",
        "name": "New Year's Day",
        "countryCode": "AD",
        "fixed": true,
        "global": true,
        "counties": null,
        "launchYear": null,
        "types": [
            "Public"
        ]
    },
    {
        "date": "2024-01-06",
        "localName": "Reis",
        "name": "Epiphany",
        "countryCode": "AD",
        "fixed": true,
        "global": true,
        "counties": null,
        "launchYear": null,
        "types": [
            "Public"
        ]
    },
    {
        "date": "2024-02-12",
        "localName": "Carnaval",
        "name": "Carnival",
        "countryCode": "AD",
        "fixed": false,
        "global": true,
        "counties": null,
        "launchYear": null,
        "types": [
            "Public"
        ]
    },
    {
        "date": "2024-03-14",
        "localName": "Dia de la Constituci\u00f3",
        "name": "Constitution Day",
        "countryCode": "AD",
        "fixed": true,
        "global": true,
        "counties": null,
        "launchYear": null,
        "types": [
            "Public"
        ]
    },
    {
        "date": "2024-03-29",
        "localName": "Divendres Sant",
        "name": "Good Friday",
        "countryCode": "AD",
        "fixed": false,
        "global": true,
        "counties": null,
        "launchYear": null,
        "types": [
            "Public"
        ]
    },
    {
        "date": "2024-04-01",
        "localName": "Dilluns de Pasqua",
        "name": "Easter Monday",
        "countryCode": "AD",
        "fixed": false,
        "global": true,
        "counties": null,
        "launchYear": null,
        "types": [
            "Public"
        ]
    },
    {
        "date": "2024-05-01",
        "localName": "Festa del Treball",
        "name": "Labour Day",
        "countryCode": "AD",
        "fixed": true,
        "global": true,
        "counties": null,
        "launchYear": null,
        "types": [
            "Public"
        ]
    },
    {
        "date": "2024-05-20",
        "localName": "Dilluns de Pentecosta",
        "name": "Whit Monday",
        "countryCode": "AD",
        "fixed": false,
        "global": true,
        "counties": null,
        "launchYear": null,
        "types": [
            "Public"
        ]
    },
    {
        "date": "2024-08-15",
        "localName": "Assumpci\u00f3",
        "name": "Assumption Day",
        "countryCode": "AD",
        "fixed": true,
        "global": true,
        "counties": null,
        "launchYear": null,
        "types": [
            "Public"
        ]
    },
    {
        "date": "2024-09-08",
        "localName": "Mare de D\u00e9u de Meritxell",
        "name": "National Holiday",
        "countryCode": "AD",
        "fixed": true,
        "global": true,
        "counties": null,
        "launchYear": null,
        "types": [
            "Public"
        ]
    },
    {
        "date": "2024-11-01",
        "localName": "Tots Sants",
        "name": "All Saints' Day",
        "countryCode": "AD",
        "fixed": true,
        "global": true,
        "counties": null,
        "launchYear": null,
        "types": [
            "Public"
        ]
    },
    {
        "date": "2024-12-08",
        "localName": "Immaculada Concepci\u00f3",
        "name": "Immaculate Conception",
        "countryCode": "AD",
        "fixed": true,
        "global": true,
        "counties": null,
        "launchYear": null,
        "types": [
            "Public"
        ]
    },
    {
        "date": "2024-12-25",
        "localName": "Nadal",
        "name": "Christmas Day",
        "countryCode": "AD",
        "fixed": true,
        "global": true,
        "counties": null,
        "launchYear": null,
        "types": [
            "Public"
        ]
    },
    {
        "date": "2024-12-26",
        "localName": "Sant Esteve",
        "name": "St. Stephen's Day",
        "countryCode": "AD",
        "fixed": true,
        "global": true,
        "counties": null,
        "launchYear": null,
        "types": [
            "Public"
        ]
    }
]