[
    {
        "date": "2024-05-01",
        "localName": "D\u00eda del trabajo",
        "name": "Labor Day",
        "countryCode": "SV",
        "fixed": true,
        "global": true,
        "counties": null,
        "launchYear": null,
        "types": [
            "Public"
        ]
    },
    {
        "date": "2024-05-03",
        "localName": "D\u00eda de la Cru",
        "name": "The Day of the Cross",
        "countryCode": "SV",
        "fixed": true,
        "global": true,
        "counties": null,
        "launchYear": null,
        "types": [
            "Public"
        ]
    },
    {
        "date": "2024-05-07",
        "localName": "D\u00eda del Soldado",
        "name": "Soldiers' Day",
        "countryCode": "SV",
        "fixed": true,
        "global": true,
        "counties": null,
        "launchYear": null,
        "types": [
            "Public"
        ]
    },
    {
        "date": "2024-05-10",
        "localName": "D\u00eda de las Madres",
        "name": "Mother's Day",
        "countryCode": "SV",
        "fixed": true,
        "global": true,
        "counties": null,
        "launchYear": null,
        "types": [
            "Public"
        ]
    },
    {
        "date": "2024-05-10",
        "localName": "D\u00eda del Padre",
        "name": "Father's Day",
        "countryCode": "SV",
        "fixed": true,
        "global": true,
        "counties": null,
        "launchYear": null,
        "types": [
            "Public"
        ]
    },
    {
        "date": "2024-08-01",
        "localName": "Fiestas de agosto",
        "name": "August Festivals",
        "countryCode": "SV",
        "fixed": true,
        "global": true,
        "counties": null,
        "launchYear": null,
        "types": [
            "Public"
        ]
    },
    {
        "date": "2024-08-02",
        "localName": "Fiestas de agosto",
        "name": "August Festivals",
        "countryCode": "SV",
        "fixed": true,
        "global": true,
        "counties": null,
        "launchYear": null,
        "types": [
            "Public"
        ]
    },
    {
        "date": "2024-08-03",
        "localName": "Fiestas de agosto",
        "name": "August Festivals",
        "countryCode": "SV",
        "fixed": true,
        "global": true,
        "counties": null,
        "launchYear": null,
        "types": [
            "Public"
        ]
    },
    {
        "date": "2024-08-04",
        "localName": "Fiestas de agosto",
        "name": "August Festivals",
        "countryCode": "SV",
        "fixed": true,
        "global": true,
        "counties": null,
        "launchYear": null,
        "types": [
            "Public"
        ]
    },
    {
        "date": "2024-08-05",
        "localName": "Fiestas de agosto",
        "name": "August Festivals",
        "countryCode": "SV",
        "fixed": true,
        "global": true,
        "counties": null,
        "launchYear": null,
        "types": [
            "Public"
        ]
    },
    {
        "date": "2024-08-06",
        "localName": "Fiestas de agosto",
        "name": "August Festivals",
        "countryCode": "SV",
        "fixed": true,
        "global": true,
        "counties": null,
        "launchYear": null,
        "types": [
            "Public"
        ]
    },
    {
        "date": "2024-08-07",
        "localName": "Fiestas de agosto",
        "name": "August Festivals",
        "countryCode": "SV",
        "fixed": true,
        "global": true,
        "counties": null,
        "launchYear": null,
        "types": [
            "Public"
        ]
    },
    {
        "date": "2024-09-15",
        "localName": "D\u00eda de la Independencia",
        "name": "Independence Day",
        "countryCode": "SV",
        "fixed": true,
        "global": true,
        "counties": null,
        "launchYear": null,
        "types": [
            "Public"
        ]
    },
    {
        "date": "2024-10-01",
        "localName": "D\u00eda del ni\u00f1o",
        "name": "Children's Day",
        "countryCode": "SV",
        "fixed": true,
        "global": true,
        "counties": null,
        "launchYear": null,
        "types": [
            "Public"
        ]
    },
    {
        "date": "2024-10-12",
        "localName": "D\u00eda de la raza",
        "name": "Ethnic Pride Day",
        "countryCode": "SV",
        "fixed": true,
        "global": true,
        "counties": null,
        "launchYear": null,
        "types": [
            "Public"
        ]
    },
    {
        "date": "2024-11-02",
        "localName": "El d\u00eda de los difuntos",
        "name": "Day of the Dead",
        "countryCode": "SV",
        "fixed": true,
        "global": true,
        "counties": null,
        "launchYear": null,
        "types": [
            "Public"
        ]
    },
    {
        "date": "2024-11-07",
        "localName": "Festival Nacional De La Pupusa",
        "name": "National Pupusa Festival",
        "countryCode": "SV",
        "fixed": true,
        "global": true,
        "counties": null,
        "launchYear": null,
        "types": [
            "Public"
        ]
    },
    {
        "date": "2024-11-08",
        "localName": "Festival Nacional De La Pupusa",
        "name": "National Pupusa Festival",
        "countryCode": "SV",
        "fixed": true,
        "global": true,
        "counties": null,
        "launchYear": null,
        "types": [
            "Public"
        ]
    },
    {
        "date": "2024-11-09",
        "localName": "Festival Nacional De La Pupusa",
        "name": "National Pupusa Festival",
        "countryCode": "SV",
        "fixed": true,
        "global": true,
        "counties": null,
        "launchYear": null,
        "types": [
            "Public"
        ]
    },
    {
        "date": "2024-11-10",
        "localName": "Festival Nacional De La Pupusa",
        "name": "National Pupusa Festival",
        "countryCode": "SV",
        "fixed": true,
        "global": true,
        "counties": null,
        "launchYear": null,
        "types": [
            "Public"
        ]
    },
    {
        "date": "2024-11-11",
        "localName": "Festival Nacional De La Pupusa",
        "name": "National Pupusa Festival",
        "countryCode": "SV",
        "fixed": true,
        "global": true,
        "counties": null,
        "launchYear": null,
        "types": [
            "Public"
        ]
    },
    {
        "date": "2024-11-12",
        "localName": "Festival Nacional De La Pupusa",
        "name": "National Pupusa Festival",
        "countryCode": "SV",
        "fixed": true,
        "global": true,
        "counties": null,
        "launchYear": null,
        "types": [
            "Public"
        ]
    },
    {
        "date": "2024-11-13",
        "localName": "Festival Nacional De La Pupusa",
        "name": "National Pupusa Festival",
        "countryCode": "SV",
        "fixed": true,
        "global": true,
        "counties": null,
        "launchYear": null,
        "types": [
            "Public"
        ]
    },
    {
        "date": "2024-11-21",
        "localName": "Dia de la Reina de la Paz",
        "name": "Day of the Queen of Peace",
        "countryCode": "SV",
        "fixed": true,
        "global": true,
        "counties": null,
        "launchYear": null,
        "types": [
            "Public"
        ]
    },
    {
        "date": "2024-12-25",
        "localName": "Noche Buena",
        "name": "Christmas Day",
        "countryCode": "SV",
        "fixed": true,
        "global": true,
        "counties": null,
        "launchYear": null,
        "types": [
            "Public"
        ]
    },
    {
        "date": "2024-12-31",
        "localName": "Fin de a\u00f1o",
        "name": "New Year's Eve",
        "countryCode": "SV",
        "fixed": true,
        "global": true,
        "counties": null,
        "launchYear": null,
        "types": [
            "Public"
        ]
    }
]